{
  "name": "Digital advertising platform  reklamstore",
  "documents": {
    "Trackers Policy": {
      "fetch": "https://www.reklamstore.com/cookie-policy/",
      "select": "body"
    },
    "Terms of Service": {
      "fetch": "https://www.reklamstore.com/terms-and-conditions",
      "select": "body"
    },
    "Privacy Policy": {
      "fetch": "https://www.reklamstore.com/privacy-policy/",
      "select": "html > body > div:first-of-type > div:nth-of-type(2) > div > article > div > div > div > div"
    }
  }
}
